url_version_finder/__init__.py
url_version_finder/decorators.py
url_version_finder-0.0.1.dist-info/METADATA
url_version_finder-0.0.1.dist-info/WHEEL
url_version_finder-0.0.1.dist-info/RECORD
